setup.py
openvino_colab/__init__.py
openvino_colab/code.py
openvino_colab.egg-info/PKG-INFO
openvino_colab.egg-info/SOURCES.txt
openvino_colab.egg-info/dependency_links.txt
openvino_colab.egg-info/not-zip-safe
openvino_colab.egg-info/top_level.txt