Metadata-Version: 1.0
Name: openvino-colab
Version: 3.1.2
Summary: OpenVINO toolkit package for Google Colab
Home-page: UNKNOWN
Author: Muhammad Ali
Author-email: malirashid1994@gmail.com
License: UNKNOWN
Platform: UNKNOWN
